[{"arguments":["clang","-Wno-documentation-unknown-command","-Wno-unknown-warning-option","-Wno-unknown-pragmas","-nostdinc","-nostdinc++","-g","-std=gnu++1z","-Wall","-Wextra","-Wextra","-fexceptions","-mthreads","-fsyntax-only","-m64","--target=x86_64-w64-mingw32","-DUNICODE","-D_UNICODE","-DWIN32","-DMINGW_HAS_SECURE_API","-DQT_QML_DEBUG","-DQT_WIDGETS_LIB","-DQT_GUI_LIB","-DQT_NETWORK_LIB","-DQT_CORE_LIB","-DQT_NEEDS_QMAIN","-DQ_CREATOR_RUN","-DQT_ANNOTATE_FUNCTION(x)=__attribute__((annotate(#x)))","-ID:\\Qt6\\Tools\\QtCreator\\share\\qtcreator\\cplusplus\\wrappedMingwHeaders","-ID:\\Qt6\\Tools\\QtCreator\\share\\qtcreator\\cplusplus\\wrappedQtHeaders","-ID:\\Qt6\\Tools\\QtCreator\\share\\qtcreator\\cplusplus\\wrappedQtHeaders\\QtCore","-IE:\\project\\llfc_chat","-ID:\\Qt6\\6.10.0\\mingw_64\\include","-ID:\\Qt6\\6.10.0\\mingw_64\\include\\QtWidgets","-ID:\\Qt6\\6.10.0\\mingw_64\\include\\QtGui","-ID:\\Qt6\\6.10.0\\mingw_64\\include\\QtNetwork","-ID:\\Qt6\\6.10.0\\mingw_64\\include\\QtCore","-IE:\\project\\llfc_chat\\build\\Desktop_Qt_6_10_0_MinGW_64_bit-Debug\\debug","-IE:\\project\\llfc_chat\\build\\Desktop_Qt_6_10_0_MinGW_64_bit-Debug","-ID:\\Qt6\\6.10.0\\mingw_64\\mkspecs\\win32-g++","-isystem","D:\\Qt6\\Tools\\mingw1310_64\\lib\\gcc\\x86_64-w64-mingw32\\13.1.0\\include\\c++","-isystem","D:\\Qt6\\Tools\\mingw1310_64\\lib\\gcc\\x86_64-w64-mingw32\\13.1.0\\include\\c++\\x86_64-w64-mingw32","-isystem","D:\\Qt6\\Tools\\mingw1310_64\\lib\\gcc\\x86_64-w64-mingw32\\13.1.0\\include\\c++\\backward","-isystem","D:\\Qt6\\Tools\\QtCreator\\bin\\clang\\lib\\clang\\20\\include","-isystem","D:\\Qt6\\Tools\\mingw1310_64\\x86_64-w64-mingw32\\include","-fmessage-length=0","-fdiagnostics-show-note-include-stack","-fretain-comments-from-system-headers","-fmacro-backtrace-limit=0","-ferror-limit=1000","-x","c++","E:\\project\\llfc_chat\\Reset.cpp"],"directory":"E:/project/llfc_chat/build/Desktop_Qt_6_10_0_MinGW_64_bit-Debug/.qtc_clangd","file":"E:/project/llfc_chat/Reset.cpp"},{"arguments":["clang","-Wno-documentation-unknown-command","-Wno-unknown-warning-option","-Wno-unknown-pragmas","-nostdinc","-nostdinc++","-g","-std=gnu++1z","-Wall","-Wextra","-Wextra","-fexceptions","-mthreads","-fsyntax-only","-m64","--target=x86_64-w64-mingw32","-DUNICODE","-D_UNICODE","-DWIN32","-DMINGW_HAS_SECURE_API","-DQT_QML_DEBUG","-DQT_WIDGETS_LIB","-DQT_GUI_LIB","-DQT_NETWORK_LIB","-DQT_CORE_LIB","-DQT_NEEDS_QMAIN","-DQ_CREATOR_RUN","-DQT_ANNOTATE_FUNCTION(x)=__attribute__((annotate(#x)))","-ID:\\Qt6\\Tools\\QtCreator\\share\\qtcreator\\cplusplus\\wrappedMingwHeaders","-ID:\\Qt6\\Tools\\QtCreator\\share\\qtcreator\\cplusplus\\wrappedQtHeaders","-ID:\\Qt6\\Tools\\QtCreator\\share\\qtcreator\\cplusplus\\wrappedQtHeaders\\QtCore","-IE:\\project\\llfc_chat","-ID:\\Qt6\\6.10.0\\mingw_64\\include","-ID:\\Qt6\\6.10.0\\mingw_64\\include\\QtWidgets","-ID:\\Qt6\\6.10.0\\mingw_64\\include\\QtGui","-ID:\\Qt6\\6.10.0\\mingw_64\\include\\QtNetwork","-ID:\\Qt6\\6.10.0\\mingw_64\\include\\QtCore","-IE:\\project\\llfc_chat\\build\\Desktop_Qt_6_10_0_MinGW_64_bit-Debug\\debug","-IE:\\project\\llfc_chat\\build\\Desktop_Qt_6_10_0_MinGW_64_bit-Debug","-ID:\\Qt6\\6.10.0\\mingw_64\\mkspecs\\win32-g++","-isystem","D:\\Qt6\\Tools\\mingw1310_64\\lib\\gcc\\x86_64-w64-mingw32\\13.1.0\\include\\c++","-isystem","D:\\Qt6\\Tools\\mingw1310_64\\lib\\gcc\\x86_64-w64-mingw32\\13.1.0\\include\\c++\\x86_64-w64-mingw32","-isystem","D:\\Qt6\\Tools\\mingw1310_64\\lib\\gcc\\x86_64-w64-mingw32\\13.1.0\\include\\c++\\backward","-isystem","D:\\Qt6\\Tools\\QtCreator\\bin\\clang\\lib\\clang\\20\\include","-isystem","D:\\Qt6\\Tools\\mingw1310_64\\x86_64-w64-mingw32\\include","-fmessage-length=0","-fdiagnostics-show-note-include-stack","-fretain-comments-from-system-headers","-fmacro-backtrace-limit=0","-ferror-limit=1000","-x","c++","E:\\project\\llfc_chat\\clickedlabel.cpp"],"directory":"E:/project/llfc_chat/build/Desktop_Qt_6_10_0_MinGW_64_bit-Debug/.qtc_clangd","file":"E:/project/llfc_chat/clickedlabel.cpp"},{"arguments":["clang","-Wno-documentation-unknown-command","-Wno-unknown-warning-option","-Wno-unknown-pragmas","-nostdinc","-nostdinc++","-g","-std=gnu++1z","-Wall","-Wextra","-Wextra","-fexceptions","-mthreads","-fsyntax-only","-m64","--target=x86_64-w64-mingw32","-DUNICODE","-D_UNICODE","-DWIN32","-DMINGW_HAS_SECURE_API","-DQT_QML_DEBUG","-DQT_WIDGETS_LIB","-DQT_GUI_LIB","-DQT_NETWORK_LIB","-DQT_CORE_LIB","-DQT_NEEDS_QMAIN","-DQ_CREATOR_RUN","-DQT_ANNOTATE_FUNCTION(x)=__attribute__((annotate(#x)))","-ID:\\Qt6\\Tools\\QtCreator\\share\\qtcreator\\cplusplus\\wrappedMingwHeaders","-ID:\\Qt6\\Tools\\QtCreator\\share\\qtcreator\\cplusplus\\wrappedQtHeaders","-ID:\\Qt6\\Tools\\QtCreator\\share\\qtcreator\\cplusplus\\wrappedQtHeaders\\QtCore","-IE:\\project\\llfc_chat","-ID:\\Qt6\\6.10.0\\mingw_64\\include","-ID:\\Qt6\\6.10.0\\mingw_64\\include\\QtWidgets","-ID:\\Qt6\\6.10.0\\mingw_64\\include\\QtGui","-ID:\\Qt6\\6.10.0\\mingw_64\\include\\QtNetwork","-ID:\\Qt6\\6.10.0\\mingw_64\\include\\QtCore","-IE:\\project\\llfc_chat\\build\\Desktop_Qt_6_10_0_MinGW_64_bit-Debug\\debug","-IE:\\project\\llfc_chat\\build\\Desktop_Qt_6_10_0_MinGW_64_bit-Debug","-ID:\\Qt6\\6.10.0\\mingw_64\\mkspecs\\win32-g++","-isystem","D:\\Qt6\\Tools\\mingw1310_64\\lib\\gcc\\x86_64-w64-mingw32\\13.1.0\\include\\c++","-isystem","D:\\Qt6\\Tools\\mingw1310_64\\lib\\gcc\\x86_64-w64-mingw32\\13.1.0\\include\\c++\\x86_64-w64-mingw32","-isystem","D:\\Qt6\\Tools\\mingw1310_64\\lib\\gcc\\x86_64-w64-mingw32\\13.1.0\\include\\c++\\backward","-isystem","D:\\Qt6\\Tools\\QtCreator\\bin\\clang\\lib\\clang\\20\\include","-isystem","D:\\Qt6\\Tools\\mingw1310_64\\x86_64-w64-mingw32\\include","-fmessage-length=0","-fdiagnostics-show-note-include-stack","-fretain-comments-from-system-headers","-fmacro-backtrace-limit=0","-ferror-limit=1000","-x","c++","E:\\project\\llfc_chat\\global.cpp"],"directory":"E:/project/llfc_chat/build/Desktop_Qt_6_10_0_MinGW_64_bit-Debug/.qtc_clangd","file":"E:/project/llfc_chat/global.cpp"},{"arguments":["clang","-Wno-documentation-unknown-command","-Wno-unknown-warning-option","-Wno-unknown-pragmas","-nostdinc","-nostdinc++","-g","-std=gnu++1z","-Wall","-Wextra","-Wextra","-fexceptions","-mthreads","-fsyntax-only","-m64","--target=x86_64-w64-mingw32","-DUNICODE","-D_UNICODE","-DWIN32","-DMINGW_HAS_SECURE_API","-DQT_QML_DEBUG","-DQT_WIDGETS_LIB","-DQT_GUI_LIB","-DQT_NETWORK_LIB","-DQT_CORE_LIB","-DQT_NEEDS_QMAIN","-DQ_CREATOR_RUN","-DQT_ANNOTATE_FUNCTION(x)=__attribute__((annotate(#x)))","-ID:\\Qt6\\Tools\\QtCreator\\share\\qtcreator\\cplusplus\\wrappedMingwHeaders","-ID:\\Qt6\\Tools\\QtCreator\\share\\qtcreator\\cplusplus\\wrappedQtHeaders","-ID:\\Qt6\\Tools\\QtCreator\\share\\qtcreator\\cplusplus\\wrappedQtHeaders\\QtCore","-IE:\\project\\llfc_chat","-ID:\\Qt6\\6.10.0\\mingw_64\\include","-ID:\\Qt6\\6.10.0\\mingw_64\\include\\QtWidgets","-ID:\\Qt6\\6.10.0\\mingw_64\\include\\QtGui","-ID:\\Qt6\\6.10.0\\mingw_64\\include\\QtNetwork","-ID:\\Qt6\\6.10.0\\mingw_64\\include\\QtCore","-IE:\\project\\llfc_chat\\build\\Desktop_Qt_6_10_0_MinGW_64_bit-Debug\\debug","-IE:\\project\\llfc_chat\\build\\Desktop_Qt_6_10_0_MinGW_64_bit-Debug","-ID:\\Qt6\\6.10.0\\mingw_64\\mkspecs\\win32-g++","-isystem","D:\\Qt6\\Tools\\mingw1310_64\\lib\\gcc\\x86_64-w64-mingw32\\13.1.0\\include\\c++","-isystem","D:\\Qt6\\Tools\\mingw1310_64\\lib\\gcc\\x86_64-w64-mingw32\\13.1.0\\include\\c++\\x86_64-w64-mingw32","-isystem","D:\\Qt6\\Tools\\mingw1310_64\\lib\\gcc\\x86_64-w64-mingw32\\13.1.0\\include\\c++\\backward","-isystem","D:\\Qt6\\Tools\\QtCreator\\bin\\clang\\lib\\clang\\20\\include","-isystem","D:\\Qt6\\Tools\\mingw1310_64\\x86_64-w64-mingw32\\include","-fmessage-length=0","-fdiagnostics-show-note-include-stack","-fretain-comments-from-system-headers","-fmacro-backtrace-limit=0","-ferror-limit=1000","-x","c++","E:\\project\\llfc_chat\\httpmgr.cpp"],"directory":"E:/project/llfc_chat/build/Desktop_Qt_6_10_0_MinGW_64_bit-Debug/.qtc_clangd","file":"E:/project/llfc_chat/httpmgr.cpp"},{"arguments":["clang","-Wno-documentation-unknown-command","-Wno-unknown-warning-option","-Wno-unknown-pragmas","-nostdinc","-nostdinc++","-g","-std=gnu++1z","-Wall","-Wextra","-Wextra","-fexceptions","-mthreads","-fsyntax-only","-m64","--target=x86_64-w64-mingw32","-DUNICODE","-D_UNICODE","-DWIN32","-DMINGW_HAS_SECURE_API","-DQT_QML_DEBUG","-DQT_WIDGETS_LIB","-DQT_GUI_LIB","-DQT_NETWORK_LIB","-DQT_CORE_LIB","-DQT_NEEDS_QMAIN","-DQ_CREATOR_RUN","-DQT_ANNOTATE_FUNCTION(x)=__attribute__((annotate(#x)))","-ID:\\Qt6\\Tools\\QtCreator\\share\\qtcreator\\cplusplus\\wrappedMingwHeaders","-ID:\\Qt6\\Tools\\QtCreator\\share\\qtcreator\\cplusplus\\wrappedQtHeaders","-ID:\\Qt6\\Tools\\QtCreator\\share\\qtcreator\\cplusplus\\wrappedQtHeaders\\QtCore","-IE:\\project\\llfc_chat","-ID:\\Qt6\\6.10.0\\mingw_64\\include","-ID:\\Qt6\\6.10.0\\mingw_64\\include\\QtWidgets","-ID:\\Qt6\\6.10.0\\mingw_64\\include\\QtGui","-ID:\\Qt6\\6.10.0\\mingw_64\\include\\QtNetwork","-ID:\\Qt6\\6.10.0\\mingw_64\\include\\QtCore","-IE:\\project\\llfc_chat\\build\\Desktop_Qt_6_10_0_MinGW_64_bit-Debug\\debug","-IE:\\project\\llfc_chat\\build\\Desktop_Qt_6_10_0_MinGW_64_bit-Debug","-ID:\\Qt6\\6.10.0\\mingw_64\\mkspecs\\win32-g++","-isystem","D:\\Qt6\\Tools\\mingw1310_64\\lib\\gcc\\x86_64-w64-mingw32\\13.1.0\\include\\c++","-isystem","D:\\Qt6\\Tools\\mingw1310_64\\lib\\gcc\\x86_64-w64-mingw32\\13.1.0\\include\\c++\\x86_64-w64-mingw32","-isystem","D:\\Qt6\\Tools\\mingw1310_64\\lib\\gcc\\x86_64-w64-mingw32\\13.1.0\\include\\c++\\backward","-isystem","D:\\Qt6\\Tools\\QtCreator\\bin\\clang\\lib\\clang\\20\\include","-isystem","D:\\Qt6\\Tools\\mingw1310_64\\x86_64-w64-mingw32\\include","-fmessage-length=0","-fdiagnostics-show-note-include-stack","-fretain-comments-from-system-headers","-fmacro-backtrace-limit=0","-ferror-limit=1000","-x","c++","E:\\project\\llfc_chat\\login.cpp"],"directory":"E:/project/llfc_chat/build/Desktop_Qt_6_10_0_MinGW_64_bit-Debug/.qtc_clangd","file":"E:/project/llfc_chat/login.cpp"},{"arguments":["clang","-Wno-documentation-unknown-command","-Wno-unknown-warning-option","-Wno-unknown-pragmas","-nostdinc","-nostdinc++","-g","-std=gnu++1z","-Wall","-Wextra","-Wextra","-fexceptions","-mthreads","-fsyntax-only","-m64","--target=x86_64-w64-mingw32","-DUNICODE","-D_UNICODE","-DWIN32","-DMINGW_HAS_SECURE_API","-DQT_QML_DEBUG","-DQT_WIDGETS_LIB","-DQT_GUI_LIB","-DQT_NETWORK_LIB","-DQT_CORE_LIB","-DQT_NEEDS_QMAIN","-DQ_CREATOR_RUN","-DQT_ANNOTATE_FUNCTION(x)=__attribute__((annotate(#x)))","-ID:\\Qt6\\Tools\\QtCreator\\share\\qtcreator\\cplusplus\\wrappedMingwHeaders","-ID:\\Qt6\\Tools\\QtCreator\\share\\qtcreator\\cplusplus\\wrappedQtHeaders","-ID:\\Qt6\\Tools\\QtCreator\\share\\qtcreator\\cplusplus\\wrappedQtHeaders\\QtCore","-IE:\\project\\llfc_chat","-ID:\\Qt6\\6.10.0\\mingw_64\\include","-ID:\\Qt6\\6.10.0\\mingw_64\\include\\QtWidgets","-ID:\\Qt6\\6.10.0\\mingw_64\\include\\QtGui","-ID:\\Qt6\\6.10.0\\mingw_64\\include\\QtNetwork","-ID:\\Qt6\\6.10.0\\mingw_64\\include\\QtCore","-IE:\\project\\llfc_chat\\build\\Desktop_Qt_6_10_0_MinGW_64_bit-Debug\\debug","-IE:\\project\\llfc_chat\\build\\Desktop_Qt_6_10_0_MinGW_64_bit-Debug","-ID:\\Qt6\\6.10.0\\mingw_64\\mkspecs\\win32-g++","-isystem","D:\\Qt6\\Tools\\mingw1310_64\\lib\\gcc\\x86_64-w64-mingw32\\13.1.0\\include\\c++","-isystem","D:\\Qt6\\Tools\\mingw1310_64\\lib\\gcc\\x86_64-w64-mingw32\\13.1.0\\include\\c++\\x86_64-w64-mingw32","-isystem","D:\\Qt6\\Tools\\mingw1310_64\\lib\\gcc\\x86_64-w64-mingw32\\13.1.0\\include\\c++\\backward","-isystem","D:\\Qt6\\Tools\\QtCreator\\bin\\clang\\lib\\clang\\20\\include","-isystem","D:\\Qt6\\Tools\\mingw1310_64\\x86_64-w64-mingw32\\include","-fmessage-length=0","-fdiagnostics-show-note-include-stack","-fretain-comments-from-system-headers","-fmacro-backtrace-limit=0","-ferror-limit=1000","-x","c++","E:\\project\\llfc_chat\\main.cpp"],"directory":"E:/project/llfc_chat/build/Desktop_Qt_6_10_0_MinGW_64_bit-Debug/.qtc_clangd","file":"E:/project/llfc_chat/main.cpp"},{"arguments":["clang","-Wno-documentation-unknown-command","-Wno-unknown-warning-option","-Wno-unknown-pragmas","-nostdinc","-nostdinc++","-g","-std=gnu++1z","-Wall","-Wextra","-Wextra","-fexceptions","-mthreads","-fsyntax-only","-m64","--target=x86_64-w64-mingw32","-DUNICODE","-D_UNICODE","-DWIN32","-DMINGW_HAS_SECURE_API","-DQT_QML_DEBUG","-DQT_WIDGETS_LIB","-DQT_GUI_LIB","-DQT_NETWORK_LIB","-DQT_CORE_LIB","-DQT_NEEDS_QMAIN","-DQ_CREATOR_RUN","-DQT_ANNOTATE_FUNCTION(x)=__attribute__((annotate(#x)))","-ID:\\Qt6\\Tools\\QtCreator\\share\\qtcreator\\cplusplus\\wrappedMingwHeaders","-ID:\\Qt6\\Tools\\QtCreator\\share\\qtcreator\\cplusplus\\wrappedQtHeaders","-ID:\\Qt6\\Tools\\QtCreator\\share\\qtcreator\\cplusplus\\wrappedQtHeaders\\QtCore","-IE:\\project\\llfc_chat","-ID:\\Qt6\\6.10.0\\mingw_64\\include","-ID:\\Qt6\\6.10.0\\mingw_64\\include\\QtWidgets","-ID:\\Qt6\\6.10.0\\mingw_64\\include\\QtGui","-ID:\\Qt6\\6.10.0\\mingw_64\\include\\QtNetwork","-ID:\\Qt6\\6.10.0\\mingw_64\\include\\QtCore","-IE:\\project\\llfc_chat\\build\\Desktop_Qt_6_10_0_MinGW_64_bit-Debug\\debug","-IE:\\project\\llfc_chat\\build\\Desktop_Qt_6_10_0_MinGW_64_bit-Debug","-ID:\\Qt6\\6.10.0\\mingw_64\\mkspecs\\win32-g++","-isystem","D:\\Qt6\\Tools\\mingw1310_64\\lib\\gcc\\x86_64-w64-mingw32\\13.1.0\\include\\c++","-isystem","D:\\Qt6\\Tools\\mingw1310_64\\lib\\gcc\\x86_64-w64-mingw32\\13.1.0\\include\\c++\\x86_64-w64-mingw32","-isystem","D:\\Qt6\\Tools\\mingw1310_64\\lib\\gcc\\x86_64-w64-mingw32\\13.1.0\\include\\c++\\backward","-isystem","D:\\Qt6\\Tools\\QtCreator\\bin\\clang\\lib\\clang\\20\\include","-isystem","D:\\Qt6\\Tools\\mingw1310_64\\x86_64-w64-mingw32\\include","-fmessage-length=0","-fdiagnostics-show-note-include-stack","-fretain-comments-from-system-headers","-fmacro-backtrace-limit=0","-ferror-limit=1000","-x","c++","E:\\project\\llfc_chat\\mainwindow.cpp"],"directory":"E:/project/llfc_chat/build/Desktop_Qt_6_10_0_MinGW_64_bit-Debug/.qtc_clangd","file":"E:/project/llfc_chat/mainwindow.cpp"},{"arguments":["clang","-Wno-documentation-unknown-command","-Wno-unknown-warning-option","-Wno-unknown-pragmas","-nostdinc","-nostdinc++","-g","-std=gnu++1z","-Wall","-Wextra","-Wextra","-fexceptions","-mthreads","-fsyntax-only","-m64","--target=x86_64-w64-mingw32","-DUNICODE","-D_UNICODE","-DWIN32","-DMINGW_HAS_SECURE_API","-DQT_QML_DEBUG","-DQT_WIDGETS_LIB","-DQT_GUI_LIB","-DQT_NETWORK_LIB","-DQT_CORE_LIB","-DQT_NEEDS_QMAIN","-DQ_CREATOR_RUN","-DQT_ANNOTATE_FUNCTION(x)=__attribute__((annotate(#x)))","-ID:\\Qt6\\Tools\\QtCreator\\share\\qtcreator\\cplusplus\\wrappedMingwHeaders","-ID:\\Qt6\\Tools\\QtCreator\\share\\qtcreator\\cplusplus\\wrappedQtHeaders","-ID:\\Qt6\\Tools\\QtCreator\\share\\qtcreator\\cplusplus\\wrappedQtHeaders\\QtCore","-IE:\\project\\llfc_chat","-ID:\\Qt6\\6.10.0\\mingw_64\\include","-ID:\\Qt6\\6.10.0\\mingw_64\\include\\QtWidgets","-ID:\\Qt6\\6.10.0\\mingw_64\\include\\QtGui","-ID:\\Qt6\\6.10.0\\mingw_64\\include\\QtNetwork","-ID:\\Qt6\\6.10.0\\mingw_64\\include\\QtCore","-IE:\\project\\llfc_chat\\build\\Desktop_Qt_6_10_0_MinGW_64_bit-Debug\\debug","-IE:\\project\\llfc_chat\\build\\Desktop_Qt_6_10_0_MinGW_64_bit-Debug","-ID:\\Qt6\\6.10.0\\mingw_64\\mkspecs\\win32-g++","-isystem","D:\\Qt6\\Tools\\mingw1310_64\\lib\\gcc\\x86_64-w64-mingw32\\13.1.0\\include\\c++","-isystem","D:\\Qt6\\Tools\\mingw1310_64\\lib\\gcc\\x86_64-w64-mingw32\\13.1.0\\include\\c++\\x86_64-w64-mingw32","-isystem","D:\\Qt6\\Tools\\mingw1310_64\\lib\\gcc\\x86_64-w64-mingw32\\13.1.0\\include\\c++\\backward","-isystem","D:\\Qt6\\Tools\\QtCreator\\bin\\clang\\lib\\clang\\20\\include","-isystem","D:\\Qt6\\Tools\\mingw1310_64\\x86_64-w64-mingw32\\include","-fmessage-length=0","-fdiagnostics-show-note-include-stack","-fretain-comments-from-system-headers","-fmacro-backtrace-limit=0","-ferror-limit=1000","-x","c++","E:\\project\\llfc_chat\\register.cpp"],"directory":"E:/project/llfc_chat/build/Desktop_Qt_6_10_0_MinGW_64_bit-Debug/.qtc_clangd","file":"E:/project/llfc_chat/register.cpp"},{"arguments":["clang","-Wno-documentation-unknown-command","-Wno-unknown-warning-option","-Wno-unknown-pragmas","-nostdinc","-nostdinc++","-g","-std=gnu++1z","-Wall","-Wextra","-Wextra","-fexceptions","-mthreads","-fsyntax-only","-m64","--target=x86_64-w64-mingw32","-DUNICODE","-D_UNICODE","-DWIN32","-DMINGW_HAS_SECURE_API","-DQT_QML_DEBUG","-DQT_WIDGETS_LIB","-DQT_GUI_LIB","-DQT_NETWORK_LIB","-DQT_CORE_LIB","-DQT_NEEDS_QMAIN","-DQ_CREATOR_RUN","-DQT_ANNOTATE_FUNCTION(x)=__attribute__((annotate(#x)))","-ID:\\Qt6\\Tools\\QtCreator\\share\\qtcreator\\cplusplus\\wrappedMingwHeaders","-ID:\\Qt6\\Tools\\QtCreator\\share\\qtcreator\\cplusplus\\wrappedQtHeaders","-ID:\\Qt6\\Tools\\QtCreator\\share\\qtcreator\\cplusplus\\wrappedQtHeaders\\QtCore","-IE:\\project\\llfc_chat","-ID:\\Qt6\\6.10.0\\mingw_64\\include","-ID:\\Qt6\\6.10.0\\mingw_64\\include\\QtWidgets","-ID:\\Qt6\\6.10.0\\mingw_64\\include\\QtGui","-ID:\\Qt6\\6.10.0\\mingw_64\\include\\QtNetwork","-ID:\\Qt6\\6.10.0\\mingw_64\\include\\QtCore","-IE:\\project\\llfc_chat\\build\\Desktop_Qt_6_10_0_MinGW_64_bit-Debug\\debug","-IE:\\project\\llfc_chat\\build\\Desktop_Qt_6_10_0_MinGW_64_bit-Debug","-ID:\\Qt6\\6.10.0\\mingw_64\\mkspecs\\win32-g++","-isystem","D:\\Qt6\\Tools\\mingw1310_64\\lib\\gcc\\x86_64-w64-mingw32\\13.1.0\\include\\c++","-isystem","D:\\Qt6\\Tools\\mingw1310_64\\lib\\gcc\\x86_64-w64-mingw32\\13.1.0\\include\\c++\\x86_64-w64-mingw32","-isystem","D:\\Qt6\\Tools\\mingw1310_64\\lib\\gcc\\x86_64-w64-mingw32\\13.1.0\\include\\c++\\backward","-isystem","D:\\Qt6\\Tools\\QtCreator\\bin\\clang\\lib\\clang\\20\\include","-isystem","D:\\Qt6\\Tools\\mingw1310_64\\x86_64-w64-mingw32\\include","-fmessage-length=0","-fdiagnostics-show-note-include-stack","-fretain-comments-from-system-headers","-fmacro-backtrace-limit=0","-ferror-limit=1000","-x","c++","E:\\project\\llfc_chat\\registeryes.cpp"],"directory":"E:/project/llfc_chat/build/Desktop_Qt_6_10_0_MinGW_64_bit-Debug/.qtc_clangd","file":"E:/project/llfc_chat/registeryes.cpp"},{"arguments":["clang","-Wno-documentation-unknown-command","-Wno-unknown-warning-option","-Wno-unknown-pragmas","-nostdinc","-nostdinc++","-g","-std=gnu++1z","-Wall","-Wextra","-Wextra","-fexceptions","-mthreads","-fsyntax-only","-m64","--target=x86_64-w64-mingw32","-DUNICODE","-D_UNICODE","-DWIN32","-DMINGW_HAS_SECURE_API","-DQT_QML_DEBUG","-DQT_WIDGETS_LIB","-DQT_GUI_LIB","-DQT_NETWORK_LIB","-DQT_CORE_LIB","-DQT_NEEDS_QMAIN","-DQ_CREATOR_RUN","-DQT_ANNOTATE_FUNCTION(x)=__attribute__((annotate(#x)))","-ID:\\Qt6\\Tools\\QtCreator\\share\\qtcreator\\cplusplus\\wrappedMingwHeaders","-ID:\\Qt6\\Tools\\QtCreator\\share\\qtcreator\\cplusplus\\wrappedQtHeaders","-ID:\\Qt6\\Tools\\QtCreator\\share\\qtcreator\\cplusplus\\wrappedQtHeaders\\QtCore","-IE:\\project\\llfc_chat","-ID:\\Qt6\\6.10.0\\mingw_64\\include","-ID:\\Qt6\\6.10.0\\mingw_64\\include\\QtWidgets","-ID:\\Qt6\\6.10.0\\mingw_64\\include\\QtGui","-ID:\\Qt6\\6.10.0\\mingw_64\\include\\QtNetwork","-ID:\\Qt6\\6.10.0\\mingw_64\\include\\QtCore","-IE:\\project\\llfc_chat\\build\\Desktop_Qt_6_10_0_MinGW_64_bit-Debug\\debug","-IE:\\project\\llfc_chat\\build\\Desktop_Qt_6_10_0_MinGW_64_bit-Debug","-ID:\\Qt6\\6.10.0\\mingw_64\\mkspecs\\win32-g++","-isystem","D:\\Qt6\\Tools\\mingw1310_64\\lib\\gcc\\x86_64-w64-mingw32\\13.1.0\\include\\c++","-isystem","D:\\Qt6\\Tools\\mingw1310_64\\lib\\gcc\\x86_64-w64-mingw32\\13.1.0\\include\\c++\\x86_64-w64-mingw32","-isystem","D:\\Qt6\\Tools\\mingw1310_64\\lib\\gcc\\x86_64-w64-mingw32\\13.1.0\\include\\c++\\backward","-isystem","D:\\Qt6\\Tools\\QtCreator\\bin\\clang\\lib\\clang\\20\\include","-isystem","D:\\Qt6\\Tools\\mingw1310_64\\x86_64-w64-mingw32\\include","-fmessage-length=0","-fdiagnostics-show-note-include-stack","-fretain-comments-from-system-headers","-fmacro-backtrace-limit=0","-ferror-limit=1000","-x","c++","E:\\project\\llfc_chat\\tcpmgr.cpp"],"directory":"E:/project/llfc_chat/build/Desktop_Qt_6_10_0_MinGW_64_bit-Debug/.qtc_clangd","file":"E:/project/llfc_chat/tcpmgr.cpp"},{"arguments":["clang","-Wno-documentation-unknown-command","-Wno-unknown-warning-option","-Wno-unknown-pragmas","-nostdinc","-nostdinc++","-g","-std=gnu++1z","-Wall","-Wextra","-Wextra","-fexceptions","-mthreads","-fsyntax-only","-m64","--target=x86_64-w64-mingw32","-DUNICODE","-D_UNICODE","-DWIN32","-DMINGW_HAS_SECURE_API","-DQT_QML_DEBUG","-DQT_WIDGETS_LIB","-DQT_GUI_LIB","-DQT_NETWORK_LIB","-DQT_CORE_LIB","-DQT_NEEDS_QMAIN","-DQ_CREATOR_RUN","-DQT_ANNOTATE_FUNCTION(x)=__attribute__((annotate(#x)))","-ID:\\Qt6\\Tools\\QtCreator\\share\\qtcreator\\cplusplus\\wrappedMingwHeaders","-ID:\\Qt6\\Tools\\QtCreator\\share\\qtcreator\\cplusplus\\wrappedQtHeaders","-ID:\\Qt6\\Tools\\QtCreator\\share\\qtcreator\\cplusplus\\wrappedQtHeaders\\QtCore","-IE:\\project\\llfc_chat","-ID:\\Qt6\\6.10.0\\mingw_64\\include","-ID:\\Qt6\\6.10.0\\mingw_64\\include\\QtWidgets","-ID:\\Qt6\\6.10.0\\mingw_64\\include\\QtGui","-ID:\\Qt6\\6.10.0\\mingw_64\\include\\QtNetwork","-ID:\\Qt6\\6.10.0\\mingw_64\\include\\QtCore","-IE:\\project\\llfc_chat\\build\\Desktop_Qt_6_10_0_MinGW_64_bit-Debug\\debug","-IE:\\project\\llfc_chat\\build\\Desktop_Qt_6_10_0_MinGW_64_bit-Debug","-ID:\\Qt6\\6.10.0\\mingw_64\\mkspecs\\win32-g++","-isystem","D:\\Qt6\\Tools\\mingw1310_64\\lib\\gcc\\x86_64-w64-mingw32\\13.1.0\\include\\c++","-isystem","D:\\Qt6\\Tools\\mingw1310_64\\lib\\gcc\\x86_64-w64-mingw32\\13.1.0\\include\\c++\\x86_64-w64-mingw32","-isystem","D:\\Qt6\\Tools\\mingw1310_64\\lib\\gcc\\x86_64-w64-mingw32\\13.1.0\\include\\c++\\backward","-isystem","D:\\Qt6\\Tools\\QtCreator\\bin\\clang\\lib\\clang\\20\\include","-isystem","D:\\Qt6\\Tools\\mingw1310_64\\x86_64-w64-mingw32\\include","-fmessage-length=0","-fdiagnostics-show-note-include-stack","-fretain-comments-from-system-headers","-fmacro-backtrace-limit=0","-ferror-limit=1000","-x","c++","E:\\project\\llfc_chat\\timerbtn.cpp"],"directory":"E:/project/llfc_chat/build/Desktop_Qt_6_10_0_MinGW_64_bit-Debug/.qtc_clangd","file":"E:/project/llfc_chat/timerbtn.cpp"},{"arguments":["clang","-Wno-documentation-unknown-command","-Wno-unknown-warning-option","-Wno-unknown-pragmas","-nostdinc","-nostdinc++","-g","-std=gnu++1z","-Wall","-Wextra","-Wextra","-fexceptions","-mthreads","-fsyntax-only","-m64","--target=x86_64-w64-mingw32","-DUNICODE","-D_UNICODE","-DWIN32","-DMINGW_HAS_SECURE_API","-DQT_QML_DEBUG","-DQT_WIDGETS_LIB","-DQT_GUI_LIB","-DQT_NETWORK_LIB","-DQT_CORE_LIB","-DQT_NEEDS_QMAIN","-DQ_CREATOR_RUN","-DQT_ANNOTATE_FUNCTION(x)=__attribute__((annotate(#x)))","-ID:\\Qt6\\Tools\\QtCreator\\share\\qtcreator\\cplusplus\\wrappedMingwHeaders","-ID:\\Qt6\\Tools\\QtCreator\\share\\qtcreator\\cplusplus\\wrappedQtHeaders","-ID:\\Qt6\\Tools\\QtCreator\\share\\qtcreator\\cplusplus\\wrappedQtHeaders\\QtCore","-IE:\\project\\llfc_chat","-ID:\\Qt6\\6.10.0\\mingw_64\\include","-ID:\\Qt6\\6.10.0\\mingw_64\\include\\QtWidgets","-ID:\\Qt6\\6.10.0\\mingw_64\\include\\QtGui","-ID:\\Qt6\\6.10.0\\mingw_64\\include\\QtNetwork","-ID:\\Qt6\\6.10.0\\mingw_64\\include\\QtCore","-IE:\\project\\llfc_chat\\build\\Desktop_Qt_6_10_0_MinGW_64_bit-Debug\\debug","-IE:\\project\\llfc_chat\\build\\Desktop_Qt_6_10_0_MinGW_64_bit-Debug","-ID:\\Qt6\\6.10.0\\mingw_64\\mkspecs\\win32-g++","-isystem","D:\\Qt6\\Tools\\mingw1310_64\\lib\\gcc\\x86_64-w64-mingw32\\13.1.0\\include\\c++","-isystem","D:\\Qt6\\Tools\\mingw1310_64\\lib\\gcc\\x86_64-w64-mingw32\\13.1.0\\include\\c++\\x86_64-w64-mingw32","-isystem","D:\\Qt6\\Tools\\mingw1310_64\\lib\\gcc\\x86_64-w64-mingw32\\13.1.0\\include\\c++\\backward","-isystem","D:\\Qt6\\Tools\\QtCreator\\bin\\clang\\lib\\clang\\20\\include","-isystem","D:\\Qt6\\Tools\\mingw1310_64\\x86_64-w64-mingw32\\include","-fmessage-length=0","-fdiagnostics-show-note-include-stack","-fretain-comments-from-system-headers","-fmacro-backtrace-limit=0","-ferror-limit=1000","-x","c++-header","E:\\project\\llfc_chat\\clickedlabel.h"],"directory":"E:/project/llfc_chat/build/Desktop_Qt_6_10_0_MinGW_64_bit-Debug/.qtc_clangd","file":"E:/project/llfc_chat/clickedlabel.h"},{"arguments":["clang","-Wno-documentation-unknown-command","-Wno-unknown-warning-option","-Wno-unknown-pragmas","-nostdinc","-nostdinc++","-g","-std=gnu++1z","-Wall","-Wextra","-Wextra","-fexceptions","-mthreads","-fsyntax-only","-m64","--target=x86_64-w64-mingw32","-DUNICODE","-D_UNICODE","-DWIN32","-DMINGW_HAS_SECURE_API","-DQT_QML_DEBUG","-DQT_WIDGETS_LIB","-DQT_GUI_LIB","-DQT_NETWORK_LIB","-DQT_CORE_LIB","-DQT_NEEDS_QMAIN","-DQ_CREATOR_RUN","-DQT_ANNOTATE_FUNCTION(x)=__attribute__((annotate(#x)))","-ID:\\Qt6\\Tools\\QtCreator\\share\\qtcreator\\cplusplus\\wrappedMingwHeaders","-ID:\\Qt6\\Tools\\QtCreator\\share\\qtcreator\\cplusplus\\wrappedQtHeaders","-ID:\\Qt6\\Tools\\QtCreator\\share\\qtcreator\\cplusplus\\wrappedQtHeaders\\QtCore","-IE:\\project\\llfc_chat","-ID:\\Qt6\\6.10.0\\mingw_64\\include","-ID:\\Qt6\\6.10.0\\mingw_64\\include\\QtWidgets","-ID:\\Qt6\\6.10.0\\mingw_64\\include\\QtGui","-ID:\\Qt6\\6.10.0\\mingw_64\\include\\QtNetwork","-ID:\\Qt6\\6.10.0\\mingw_64\\include\\QtCore","-IE:\\project\\llfc_chat\\build\\Desktop_Qt_6_10_0_MinGW_64_bit-Debug\\debug","-IE:\\project\\llfc_chat\\build\\Desktop_Qt_6_10_0_MinGW_64_bit-Debug","-ID:\\Qt6\\6.10.0\\mingw_64\\mkspecs\\win32-g++","-isystem","D:\\Qt6\\Tools\\mingw1310_64\\lib\\gcc\\x86_64-w64-mingw32\\13.1.0\\include\\c++","-isystem","D:\\Qt6\\Tools\\mingw1310_64\\lib\\gcc\\x86_64-w64-mingw32\\13.1.0\\include\\c++\\x86_64-w64-mingw32","-isystem","D:\\Qt6\\Tools\\mingw1310_64\\lib\\gcc\\x86_64-w64-mingw32\\13.1.0\\include\\c++\\backward","-isystem","D:\\Qt6\\Tools\\QtCreator\\bin\\clang\\lib\\clang\\20\\include","-isystem","D:\\Qt6\\Tools\\mingw1310_64\\x86_64-w64-mingw32\\include","-fmessage-length=0","-fdiagnostics-show-note-include-stack","-fretain-comments-from-system-headers","-fmacro-backtrace-limit=0","-ferror-limit=1000","-x","c++-header","E:\\project\\llfc_chat\\global.h"],"directory":"E:/project/llfc_chat/build/Desktop_Qt_6_10_0_MinGW_64_bit-Debug/.qtc_clangd","file":"E:/project/llfc_chat/global.h"},{"arguments":["clang","-Wno-documentation-unknown-command","-Wno-unknown-warning-option","-Wno-unknown-pragmas","-nostdinc","-nostdinc++","-g","-std=gnu++1z","-Wall","-Wextra","-Wextra","-fexceptions","-mthreads","-fsyntax-only","-m64","--target=x86_64-w64-mingw32","-DUNICODE","-D_UNICODE","-DWIN32","-DMINGW_HAS_SECURE_API","-DQT_QML_DEBUG","-DQT_WIDGETS_LIB","-DQT_GUI_LIB","-DQT_NETWORK_LIB","-DQT_CORE_LIB","-DQT_NEEDS_QMAIN","-DQ_CREATOR_RUN","-DQT_ANNOTATE_FUNCTION(x)=__attribute__((annotate(#x)))","-ID:\\Qt6\\Tools\\QtCreator\\share\\qtcreator\\cplusplus\\wrappedMingwHeaders","-ID:\\Qt6\\Tools\\QtCreator\\share\\qtcreator\\cplusplus\\wrappedQtHeaders","-ID:\\Qt6\\Tools\\QtCreator\\share\\qtcreator\\cplusplus\\wrappedQtHeaders\\QtCore","-IE:\\project\\llfc_chat","-ID:\\Qt6\\6.10.0\\mingw_64\\include","-ID:\\Qt6\\6.10.0\\mingw_64\\include\\QtWidgets","-ID:\\Qt6\\6.10.0\\mingw_64\\include\\QtGui","-ID:\\Qt6\\6.10.0\\mingw_64\\include\\QtNetwork","-ID:\\Qt6\\6.10.0\\mingw_64\\include\\QtCore","-IE:\\project\\llfc_chat\\build\\Desktop_Qt_6_10_0_MinGW_64_bit-Debug\\debug","-IE:\\project\\llfc_chat\\build\\Desktop_Qt_6_10_0_MinGW_64_bit-Debug","-ID:\\Qt6\\6.10.0\\mingw_64\\mkspecs\\win32-g++","-isystem","D:\\Qt6\\Tools\\mingw1310_64\\lib\\gcc\\x86_64-w64-mingw32\\13.1.0\\include\\c++","-isystem","D:\\Qt6\\Tools\\mingw1310_64\\lib\\gcc\\x86_64-w64-mingw32\\13.1.0\\include\\c++\\x86_64-w64-mingw32","-isystem","D:\\Qt6\\Tools\\mingw1310_64\\lib\\gcc\\x86_64-w64-mingw32\\13.1.0\\include\\c++\\backward","-isystem","D:\\Qt6\\Tools\\QtCreator\\bin\\clang\\lib\\clang\\20\\include","-isystem","D:\\Qt6\\Tools\\mingw1310_64\\x86_64-w64-mingw32\\include","-fmessage-length=0","-fdiagnostics-show-note-include-stack","-fretain-comments-from-system-headers","-fmacro-backtrace-limit=0","-ferror-limit=1000","-x","c++-header","E:\\project\\llfc_chat\\httpmgr.h"],"directory":"E:/project/llfc_chat/build/Desktop_Qt_6_10_0_MinGW_64_bit-Debug/.qtc_clangd","file":"E:/project/llfc_chat/httpmgr.h"},{"arguments":["clang","-Wno-documentation-unknown-command","-Wno-unknown-warning-option","-Wno-unknown-pragmas","-nostdinc","-nostdinc++","-g","-std=gnu++1z","-Wall","-Wextra","-Wextra","-fexceptions","-mthreads","-fsyntax-only","-m64","--target=x86_64-w64-mingw32","-DUNICODE","-D_UNICODE","-DWIN32","-DMINGW_HAS_SECURE_API","-DQT_QML_DEBUG","-DQT_WIDGETS_LIB","-DQT_GUI_LIB","-DQT_NETWORK_LIB","-DQT_CORE_LIB","-DQT_NEEDS_QMAIN","-DQ_CREATOR_RUN","-DQT_ANNOTATE_FUNCTION(x)=__attribute__((annotate(#x)))","-ID:\\Qt6\\Tools\\QtCreator\\share\\qtcreator\\cplusplus\\wrappedMingwHeaders","-ID:\\Qt6\\Tools\\QtCreator\\share\\qtcreator\\cplusplus\\wrappedQtHeaders","-ID:\\Qt6\\Tools\\QtCreator\\share\\qtcreator\\cplusplus\\wrappedQtHeaders\\QtCore","-IE:\\project\\llfc_chat","-ID:\\Qt6\\6.10.0\\mingw_64\\include","-ID:\\Qt6\\6.10.0\\mingw_64\\include\\QtWidgets","-ID:\\Qt6\\6.10.0\\mingw_64\\include\\QtGui","-ID:\\Qt6\\6.10.0\\mingw_64\\include\\QtNetwork","-ID:\\Qt6\\6.10.0\\mingw_64\\include\\QtCore","-IE:\\project\\llfc_chat\\build\\Desktop_Qt_6_10_0_MinGW_64_bit-Debug\\debug","-IE:\\project\\llfc_chat\\build\\Desktop_Qt_6_10_0_MinGW_64_bit-Debug","-ID:\\Qt6\\6.10.0\\mingw_64\\mkspecs\\win32-g++","-isystem","D:\\Qt6\\Tools\\mingw1310_64\\lib\\gcc\\x86_64-w64-mingw32\\13.1.0\\include\\c++","-isystem","D:\\Qt6\\Tools\\mingw1310_64\\lib\\gcc\\x86_64-w64-mingw32\\13.1.0\\include\\c++\\x86_64-w64-mingw32","-isystem","D:\\Qt6\\Tools\\mingw1310_64\\lib\\gcc\\x86_64-w64-mingw32\\13.1.0\\include\\c++\\backward","-isystem","D:\\Qt6\\Tools\\QtCreator\\bin\\clang\\lib\\clang\\20\\include","-isystem","D:\\Qt6\\Tools\\mingw1310_64\\x86_64-w64-mingw32\\include","-fmessage-length=0","-fdiagnostics-show-note-include-stack","-fretain-comments-from-system-headers","-fmacro-backtrace-limit=0","-ferror-limit=1000","-x","c++-header","E:\\project\\llfc_chat\\login.h"],"directory":"E:/project/llfc_chat/build/Desktop_Qt_6_10_0_MinGW_64_bit-Debug/.qtc_clangd","file":"E:/project/llfc_chat/login.h"},{"arguments":["clang","-Wno-documentation-unknown-command","-Wno-unknown-warning-option","-Wno-unknown-pragmas","-nostdinc","-nostdinc++","-g","-std=gnu++1z","-Wall","-Wextra","-Wextra","-fexceptions","-mthreads","-fsyntax-only","-m64","--target=x86_64-w64-mingw32","-DUNICODE","-D_UNICODE","-DWIN32","-DMINGW_HAS_SECURE_API","-DQT_QML_DEBUG","-DQT_WIDGETS_LIB","-DQT_GUI_LIB","-DQT_NETWORK_LIB","-DQT_CORE_LIB","-DQT_NEEDS_QMAIN","-DQ_CREATOR_RUN","-DQT_ANNOTATE_FUNCTION(x)=__attribute__((annotate(#x)))","-ID:\\Qt6\\Tools\\QtCreator\\share\\qtcreator\\cplusplus\\wrappedMingwHeaders","-ID:\\Qt6\\Tools\\QtCreator\\share\\qtcreator\\cplusplus\\wrappedQtHeaders","-ID:\\Qt6\\Tools\\QtCreator\\share\\qtcreator\\cplusplus\\wrappedQtHeaders\\QtCore","-IE:\\project\\llfc_chat","-ID:\\Qt6\\6.10.0\\mingw_64\\include","-ID:\\Qt6\\6.10.0\\mingw_64\\include\\QtWidgets","-ID:\\Qt6\\6.10.0\\mingw_64\\include\\QtGui","-ID:\\Qt6\\6.10.0\\mingw_64\\include\\QtNetwork","-ID:\\Qt6\\6.10.0\\mingw_64\\include\\QtCore","-IE:\\project\\llfc_chat\\build\\Desktop_Qt_6_10_0_MinGW_64_bit-Debug\\debug","-IE:\\project\\llfc_chat\\build\\Desktop_Qt_6_10_0_MinGW_64_bit-Debug","-ID:\\Qt6\\6.10.0\\mingw_64\\mkspecs\\win32-g++","-isystem","D:\\Qt6\\Tools\\mingw1310_64\\lib\\gcc\\x86_64-w64-mingw32\\13.1.0\\include\\c++","-isystem","D:\\Qt6\\Tools\\mingw1310_64\\lib\\gcc\\x86_64-w64-mingw32\\13.1.0\\include\\c++\\x86_64-w64-mingw32","-isystem","D:\\Qt6\\Tools\\mingw1310_64\\lib\\gcc\\x86_64-w64-mingw32\\13.1.0\\include\\c++\\backward","-isystem","D:\\Qt6\\Tools\\QtCreator\\bin\\clang\\lib\\clang\\20\\include","-isystem","D:\\Qt6\\Tools\\mingw1310_64\\x86_64-w64-mingw32\\include","-fmessage-length=0","-fdiagnostics-show-note-include-stack","-fretain-comments-from-system-headers","-fmacro-backtrace-limit=0","-ferror-limit=1000","-x","c++-header","E:\\project\\llfc_chat\\mainwindow.h"],"directory":"E:/project/llfc_chat/build/Desktop_Qt_6_10_0_MinGW_64_bit-Debug/.qtc_clangd","file":"E:/project/llfc_chat/mainwindow.h"},{"arguments":["clang","-Wno-documentation-unknown-command","-Wno-unknown-warning-option","-Wno-unknown-pragmas","-nostdinc","-nostdinc++","-g","-std=gnu++1z","-Wall","-Wextra","-Wextra","-fexceptions","-mthreads","-fsyntax-only","-m64","--target=x86_64-w64-mingw32","-DUNICODE","-D_UNICODE","-DWIN32","-DMINGW_HAS_SECURE_API","-DQT_QML_DEBUG","-DQT_WIDGETS_LIB","-DQT_GUI_LIB","-DQT_NETWORK_LIB","-DQT_CORE_LIB","-DQT_NEEDS_QMAIN","-DQ_CREATOR_RUN","-DQT_ANNOTATE_FUNCTION(x)=__attribute__((annotate(#x)))","-ID:\\Qt6\\Tools\\QtCreator\\share\\qtcreator\\cplusplus\\wrappedMingwHeaders","-ID:\\Qt6\\Tools\\QtCreator\\share\\qtcreator\\cplusplus\\wrappedQtHeaders","-ID:\\Qt6\\Tools\\QtCreator\\share\\qtcreator\\cplusplus\\wrappedQtHeaders\\QtCore","-IE:\\project\\llfc_chat","-ID:\\Qt6\\6.10.0\\mingw_64\\include","-ID:\\Qt6\\6.10.0\\mingw_64\\include\\QtWidgets","-ID:\\Qt6\\6.10.0\\mingw_64\\include\\QtGui","-ID:\\Qt6\\6.10.0\\mingw_64\\include\\QtNetwork","-ID:\\Qt6\\6.10.0\\mingw_64\\include\\QtCore","-IE:\\project\\llfc_chat\\build\\Desktop_Qt_6_10_0_MinGW_64_bit-Debug\\debug","-IE:\\project\\llfc_chat\\build\\Desktop_Qt_6_10_0_MinGW_64_bit-Debug","-ID:\\Qt6\\6.10.0\\mingw_64\\mkspecs\\win32-g++","-isystem","D:\\Qt6\\Tools\\mingw1310_64\\lib\\gcc\\x86_64-w64-mingw32\\13.1.0\\include\\c++","-isystem","D:\\Qt6\\Tools\\mingw1310_64\\lib\\gcc\\x86_64-w64-mingw32\\13.1.0\\include\\c++\\x86_64-w64-mingw32","-isystem","D:\\Qt6\\Tools\\mingw1310_64\\lib\\gcc\\x86_64-w64-mingw32\\13.1.0\\include\\c++\\backward","-isystem","D:\\Qt6\\Tools\\QtCreator\\bin\\clang\\lib\\clang\\20\\include","-isystem","D:\\Qt6\\Tools\\mingw1310_64\\x86_64-w64-mingw32\\include","-fmessage-length=0","-fdiagnostics-show-note-include-stack","-fretain-comments-from-system-headers","-fmacro-backtrace-limit=0","-ferror-limit=1000","-x","c++-header","E:\\project\\llfc_chat\\register.h"],"directory":"E:/project/llfc_chat/build/Desktop_Qt_6_10_0_MinGW_64_bit-Debug/.qtc_clangd","file":"E:/project/llfc_chat/register.h"},{"arguments":["clang","-Wno-documentation-unknown-command","-Wno-unknown-warning-option","-Wno-unknown-pragmas","-nostdinc","-nostdinc++","-g","-std=gnu++1z","-Wall","-Wextra","-Wextra","-fexceptions","-mthreads","-fsyntax-only","-m64","--target=x86_64-w64-mingw32","-DUNICODE","-D_UNICODE","-DWIN32","-DMINGW_HAS_SECURE_API","-DQT_QML_DEBUG","-DQT_WIDGETS_LIB","-DQT_GUI_LIB","-DQT_NETWORK_LIB","-DQT_CORE_LIB","-DQT_NEEDS_QMAIN","-DQ_CREATOR_RUN","-DQT_ANNOTATE_FUNCTION(x)=__attribute__((annotate(#x)))","-ID:\\Qt6\\Tools\\QtCreator\\share\\qtcreator\\cplusplus\\wrappedMingwHeaders","-ID:\\Qt6\\Tools\\QtCreator\\share\\qtcreator\\cplusplus\\wrappedQtHeaders","-ID:\\Qt6\\Tools\\QtCreator\\share\\qtcreator\\cplusplus\\wrappedQtHeaders\\QtCore","-IE:\\project\\llfc_chat","-ID:\\Qt6\\6.10.0\\mingw_64\\include","-ID:\\Qt6\\6.10.0\\mingw_64\\include\\QtWidgets","-ID:\\Qt6\\6.10.0\\mingw_64\\include\\QtGui","-ID:\\Qt6\\6.10.0\\mingw_64\\include\\QtNetwork","-ID:\\Qt6\\6.10.0\\mingw_64\\include\\QtCore","-IE:\\project\\llfc_chat\\build\\Desktop_Qt_6_10_0_MinGW_64_bit-Debug\\debug","-IE:\\project\\llfc_chat\\build\\Desktop_Qt_6_10_0_MinGW_64_bit-Debug","-ID:\\Qt6\\6.10.0\\mingw_64\\mkspecs\\win32-g++","-isystem","D:\\Qt6\\Tools\\mingw1310_64\\lib\\gcc\\x86_64-w64-mingw32\\13.1.0\\include\\c++","-isystem","D:\\Qt6\\Tools\\mingw1310_64\\lib\\gcc\\x86_64-w64-mingw32\\13.1.0\\include\\c++\\x86_64-w64-mingw32","-isystem","D:\\Qt6\\Tools\\mingw1310_64\\lib\\gcc\\x86_64-w64-mingw32\\13.1.0\\include\\c++\\backward","-isystem","D:\\Qt6\\Tools\\QtCreator\\bin\\clang\\lib\\clang\\20\\include","-isystem","D:\\Qt6\\Tools\\mingw1310_64\\x86_64-w64-mingw32\\include","-fmessage-length=0","-fdiagnostics-show-note-include-stack","-fretain-comments-from-system-headers","-fmacro-backtrace-limit=0","-ferror-limit=1000","-x","c++-header","E:\\project\\llfc_chat\\registeryes.h"],"directory":"E:/project/llfc_chat/build/Desktop_Qt_6_10_0_MinGW_64_bit-Debug/.qtc_clangd","file":"E:/project/llfc_chat/registeryes.h"},{"arguments":["clang","-Wno-documentation-unknown-command","-Wno-unknown-warning-option","-Wno-unknown-pragmas","-nostdinc","-nostdinc++","-g","-std=gnu++1z","-Wall","-Wextra","-Wextra","-fexceptions","-mthreads","-fsyntax-only","-m64","--target=x86_64-w64-mingw32","-DUNICODE","-D_UNICODE","-DWIN32","-DMINGW_HAS_SECURE_API","-DQT_QML_DEBUG","-DQT_WIDGETS_LIB","-DQT_GUI_LIB","-DQT_NETWORK_LIB","-DQT_CORE_LIB","-DQT_NEEDS_QMAIN","-DQ_CREATOR_RUN","-DQT_ANNOTATE_FUNCTION(x)=__attribute__((annotate(#x)))","-ID:\\Qt6\\Tools\\QtCreator\\share\\qtcreator\\cplusplus\\wrappedMingwHeaders","-ID:\\Qt6\\Tools\\QtCreator\\share\\qtcreator\\cplusplus\\wrappedQtHeaders","-ID:\\Qt6\\Tools\\QtCreator\\share\\qtcreator\\cplusplus\\wrappedQtHeaders\\QtCore","-IE:\\project\\llfc_chat","-ID:\\Qt6\\6.10.0\\mingw_64\\include","-ID:\\Qt6\\6.10.0\\mingw_64\\include\\QtWidgets","-ID:\\Qt6\\6.10.0\\mingw_64\\include\\QtGui","-ID:\\Qt6\\6.10.0\\mingw_64\\include\\QtNetwork","-ID:\\Qt6\\6.10.0\\mingw_64\\include\\QtCore","-IE:\\project\\llfc_chat\\build\\Desktop_Qt_6_10_0_MinGW_64_bit-Debug\\debug","-IE:\\project\\llfc_chat\\build\\Desktop_Qt_6_10_0_MinGW_64_bit-Debug","-ID:\\Qt6\\6.10.0\\mingw_64\\mkspecs\\win32-g++","-isystem","D:\\Qt6\\Tools\\mingw1310_64\\lib\\gcc\\x86_64-w64-mingw32\\13.1.0\\include\\c++","-isystem","D:\\Qt6\\Tools\\mingw1310_64\\lib\\gcc\\x86_64-w64-mingw32\\13.1.0\\include\\c++\\x86_64-w64-mingw32","-isystem","D:\\Qt6\\Tools\\mingw1310_64\\lib\\gcc\\x86_64-w64-mingw32\\13.1.0\\include\\c++\\backward","-isystem","D:\\Qt6\\Tools\\QtCreator\\bin\\clang\\lib\\clang\\20\\include","-isystem","D:\\Qt6\\Tools\\mingw1310_64\\x86_64-w64-mingw32\\include","-fmessage-length=0","-fdiagnostics-show-note-include-stack","-fretain-comments-from-system-headers","-fmacro-backtrace-limit=0","-ferror-limit=1000","-x","c++-header","E:\\project\\llfc_chat\\reset.h"],"directory":"E:/project/llfc_chat/build/Desktop_Qt_6_10_0_MinGW_64_bit-Debug/.qtc_clangd","file":"E:/project/llfc_chat/reset.h"},{"arguments":["clang","-Wno-documentation-unknown-command","-Wno-unknown-warning-option","-Wno-unknown-pragmas","-nostdinc","-nostdinc++","-g","-std=gnu++1z","-Wall","-Wextra","-Wextra","-fexceptions","-mthreads","-fsyntax-only","-m64","--target=x86_64-w64-mingw32","-DUNICODE","-D_UNICODE","-DWIN32","-DMINGW_HAS_SECURE_API","-DQT_QML_DEBUG","-DQT_WIDGETS_LIB","-DQT_GUI_LIB","-DQT_NETWORK_LIB","-DQT_CORE_LIB","-DQT_NEEDS_QMAIN","-DQ_CREATOR_RUN","-DQT_ANNOTATE_FUNCTION(x)=__attribute__((annotate(#x)))","-ID:\\Qt6\\Tools\\QtCreator\\share\\qtcreator\\cplusplus\\wrappedMingwHeaders","-ID:\\Qt6\\Tools\\QtCreator\\share\\qtcreator\\cplusplus\\wrappedQtHeaders","-ID:\\Qt6\\Tools\\QtCreator\\share\\qtcreator\\cplusplus\\wrappedQtHeaders\\QtCore","-IE:\\project\\llfc_chat","-ID:\\Qt6\\6.10.0\\mingw_64\\include","-ID:\\Qt6\\6.10.0\\mingw_64\\include\\QtWidgets","-ID:\\Qt6\\6.10.0\\mingw_64\\include\\QtGui","-ID:\\Qt6\\6.10.0\\mingw_64\\include\\QtNetwork","-ID:\\Qt6\\6.10.0\\mingw_64\\include\\QtCore","-IE:\\project\\llfc_chat\\build\\Desktop_Qt_6_10_0_MinGW_64_bit-Debug\\debug","-IE:\\project\\llfc_chat\\build\\Desktop_Qt_6_10_0_MinGW_64_bit-Debug","-ID:\\Qt6\\6.10.0\\mingw_64\\mkspecs\\win32-g++","-isystem","D:\\Qt6\\Tools\\mingw1310_64\\lib\\gcc\\x86_64-w64-mingw32\\13.1.0\\include\\c++","-isystem","D:\\Qt6\\Tools\\mingw1310_64\\lib\\gcc\\x86_64-w64-mingw32\\13.1.0\\include\\c++\\x86_64-w64-mingw32","-isystem","D:\\Qt6\\Tools\\mingw1310_64\\lib\\gcc\\x86_64-w64-mingw32\\13.1.0\\include\\c++\\backward","-isystem","D:\\Qt6\\Tools\\QtCreator\\bin\\clang\\lib\\clang\\20\\include","-isystem","D:\\Qt6\\Tools\\mingw1310_64\\x86_64-w64-mingw32\\include","-fmessage-length=0","-fdiagnostics-show-note-include-stack","-fretain-comments-from-system-headers","-fmacro-backtrace-limit=0","-ferror-limit=1000","-x","c++-header","E:\\project\\llfc_chat\\singleton.h"],"directory":"E:/project/llfc_chat/build/Desktop_Qt_6_10_0_MinGW_64_bit-Debug/.qtc_clangd","file":"E:/project/llfc_chat/singleton.h"},{"arguments":["clang","-Wno-documentation-unknown-command","-Wno-unknown-warning-option","-Wno-unknown-pragmas","-nostdinc","-nostdinc++","-g","-std=gnu++1z","-Wall","-Wextra","-Wextra","-fexceptions","-mthreads","-fsyntax-only","-m64","--target=x86_64-w64-mingw32","-DUNICODE","-D_UNICODE","-DWIN32","-DMINGW_HAS_SECURE_API","-DQT_QML_DEBUG","-DQT_WIDGETS_LIB","-DQT_GUI_LIB","-DQT_NETWORK_LIB","-DQT_CORE_LIB","-DQT_NEEDS_QMAIN","-DQ_CREATOR_RUN","-DQT_ANNOTATE_FUNCTION(x)=__attribute__((annotate(#x)))","-ID:\\Qt6\\Tools\\QtCreator\\share\\qtcreator\\cplusplus\\wrappedMingwHeaders","-ID:\\Qt6\\Tools\\QtCreator\\share\\qtcreator\\cplusplus\\wrappedQtHeaders","-ID:\\Qt6\\Tools\\QtCreator\\share\\qtcreator\\cplusplus\\wrappedQtHeaders\\QtCore","-IE:\\project\\llfc_chat","-ID:\\Qt6\\6.10.0\\mingw_64\\include","-ID:\\Qt6\\6.10.0\\mingw_64\\include\\QtWidgets","-ID:\\Qt6\\6.10.0\\mingw_64\\include\\QtGui","-ID:\\Qt6\\6.10.0\\mingw_64\\include\\QtNetwork","-ID:\\Qt6\\6.10.0\\mingw_64\\include\\QtCore","-IE:\\project\\llfc_chat\\build\\Desktop_Qt_6_10_0_MinGW_64_bit-Debug\\debug","-IE:\\project\\llfc_chat\\build\\Desktop_Qt_6_10_0_MinGW_64_bit-Debug","-ID:\\Qt6\\6.10.0\\mingw_64\\mkspecs\\win32-g++","-isystem","D:\\Qt6\\Tools\\mingw1310_64\\lib\\gcc\\x86_64-w64-mingw32\\13.1.0\\include\\c++","-isystem","D:\\Qt6\\Tools\\mingw1310_64\\lib\\gcc\\x86_64-w64-mingw32\\13.1.0\\include\\c++\\x86_64-w64-mingw32","-isystem","D:\\Qt6\\Tools\\mingw1310_64\\lib\\gcc\\x86_64-w64-mingw32\\13.1.0\\include\\c++\\backward","-isystem","D:\\Qt6\\Tools\\QtCreator\\bin\\clang\\lib\\clang\\20\\include","-isystem","D:\\Qt6\\Tools\\mingw1310_64\\x86_64-w64-mingw32\\include","-fmessage-length=0","-fdiagnostics-show-note-include-stack","-fretain-comments-from-system-headers","-fmacro-backtrace-limit=0","-ferror-limit=1000","-x","c++-header","E:\\project\\llfc_chat\\tcpmgr.h"],"directory":"E:/project/llfc_chat/build/Desktop_Qt_6_10_0_MinGW_64_bit-Debug/.qtc_clangd","file":"E:/project/llfc_chat/tcpmgr.h"},{"arguments":["clang","-Wno-documentation-unknown-command","-Wno-unknown-warning-option","-Wno-unknown-pragmas","-nostdinc","-nostdinc++","-g","-std=gnu++1z","-Wall","-Wextra","-Wextra","-fexceptions","-mthreads","-fsyntax-only","-m64","--target=x86_64-w64-mingw32","-DUNICODE","-D_UNICODE","-DWIN32","-DMINGW_HAS_SECURE_API","-DQT_QML_DEBUG","-DQT_WIDGETS_LIB","-DQT_GUI_LIB","-DQT_NETWORK_LIB","-DQT_CORE_LIB","-DQT_NEEDS_QMAIN","-DQ_CREATOR_RUN","-DQT_ANNOTATE_FUNCTION(x)=__attribute__((annotate(#x)))","-ID:\\Qt6\\Tools\\QtCreator\\share\\qtcreator\\cplusplus\\wrappedMingwHeaders","-ID:\\Qt6\\Tools\\QtCreator\\share\\qtcreator\\cplusplus\\wrappedQtHeaders","-ID:\\Qt6\\Tools\\QtCreator\\share\\qtcreator\\cplusplus\\wrappedQtHeaders\\QtCore","-IE:\\project\\llfc_chat","-ID:\\Qt6\\6.10.0\\mingw_64\\include","-ID:\\Qt6\\6.10.0\\mingw_64\\include\\QtWidgets","-ID:\\Qt6\\6.10.0\\mingw_64\\include\\QtGui","-ID:\\Qt6\\6.10.0\\mingw_64\\include\\QtNetwork","-ID:\\Qt6\\6.10.0\\mingw_64\\include\\QtCore","-IE:\\project\\llfc_chat\\build\\Desktop_Qt_6_10_0_MinGW_64_bit-Debug\\debug","-IE:\\project\\llfc_chat\\build\\Desktop_Qt_6_10_0_MinGW_64_bit-Debug","-ID:\\Qt6\\6.10.0\\mingw_64\\mkspecs\\win32-g++","-isystem","D:\\Qt6\\Tools\\mingw1310_64\\lib\\gcc\\x86_64-w64-mingw32\\13.1.0\\include\\c++","-isystem","D:\\Qt6\\Tools\\mingw1310_64\\lib\\gcc\\x86_64-w64-mingw32\\13.1.0\\include\\c++\\x86_64-w64-mingw32","-isystem","D:\\Qt6\\Tools\\mingw1310_64\\lib\\gcc\\x86_64-w64-mingw32\\13.1.0\\include\\c++\\backward","-isystem","D:\\Qt6\\Tools\\QtCreator\\bin\\clang\\lib\\clang\\20\\include","-isystem","D:\\Qt6\\Tools\\mingw1310_64\\x86_64-w64-mingw32\\include","-fmessage-length=0","-fdiagnostics-show-note-include-stack","-fretain-comments-from-system-headers","-fmacro-backtrace-limit=0","-ferror-limit=1000","-x","c++-header","E:\\project\\llfc_chat\\timerbtn.h"],"directory":"E:/project/llfc_chat/build/Desktop_Qt_6_10_0_MinGW_64_bit-Debug/.qtc_clangd","file":"E:/project/llfc_chat/timerbtn.h"},{"arguments":["clang","-Wno-documentation-unknown-command","-Wno-unknown-warning-option","-Wno-unknown-pragmas","-nostdinc","-nostdinc++","-g","-std=gnu++1z","-Wall","-Wextra","-Wextra","-fexceptions","-mthreads","-fsyntax-only","-m64","--target=x86_64-w64-mingw32","-DUNICODE","-D_UNICODE","-DWIN32","-DMINGW_HAS_SECURE_API","-DQT_QML_DEBUG","-DQT_WIDGETS_LIB","-DQT_GUI_LIB","-DQT_NETWORK_LIB","-DQT_CORE_LIB","-DQT_NEEDS_QMAIN","-DQ_CREATOR_RUN","-DQT_ANNOTATE_FUNCTION(x)=__attribute__((annotate(#x)))","-ID:\\Qt6\\Tools\\QtCreator\\share\\qtcreator\\cplusplus\\wrappedMingwHeaders","-ID:\\Qt6\\Tools\\QtCreator\\share\\qtcreator\\cplusplus\\wrappedQtHeaders","-ID:\\Qt6\\Tools\\QtCreator\\share\\qtcreator\\cplusplus\\wrappedQtHeaders\\QtCore","-IE:\\project\\llfc_chat","-ID:\\Qt6\\6.10.0\\mingw_64\\include","-ID:\\Qt6\\6.10.0\\mingw_64\\include\\QtWidgets","-ID:\\Qt6\\6.10.0\\mingw_64\\include\\QtGui","-ID:\\Qt6\\6.10.0\\mingw_64\\include\\QtNetwork","-ID:\\Qt6\\6.10.0\\mingw_64\\include\\QtCore","-IE:\\project\\llfc_chat\\build\\Desktop_Qt_6_10_0_MinGW_64_bit-Debug\\debug","-IE:\\project\\llfc_chat\\build\\Desktop_Qt_6_10_0_MinGW_64_bit-Debug","-ID:\\Qt6\\6.10.0\\mingw_64\\mkspecs\\win32-g++","-isystem","D:\\Qt6\\Tools\\mingw1310_64\\lib\\gcc\\x86_64-w64-mingw32\\13.1.0\\include\\c++","-isystem","D:\\Qt6\\Tools\\mingw1310_64\\lib\\gcc\\x86_64-w64-mingw32\\13.1.0\\include\\c++\\x86_64-w64-mingw32","-isystem","D:\\Qt6\\Tools\\mingw1310_64\\lib\\gcc\\x86_64-w64-mingw32\\13.1.0\\include\\c++\\backward","-isystem","D:\\Qt6\\Tools\\QtCreator\\bin\\clang\\lib\\clang\\20\\include","-isystem","D:\\Qt6\\Tools\\mingw1310_64\\x86_64-w64-mingw32\\include","-fmessage-length=0","-fdiagnostics-show-note-include-stack","-fretain-comments-from-system-headers","-fmacro-backtrace-limit=0","-ferror-limit=1000","-x","c++-header","E:\\project\\llfc_chat\\build\\Desktop_Qt_6_10_0_MinGW_64_bit-Debug\\ui_login.h"],"directory":"E:/project/llfc_chat/build/Desktop_Qt_6_10_0_MinGW_64_bit-Debug/.qtc_clangd","file":"E:/project/llfc_chat/build/Desktop_Qt_6_10_0_MinGW_64_bit-Debug/ui_login.h"},{"arguments":["clang","-Wno-documentation-unknown-command","-Wno-unknown-warning-option","-Wno-unknown-pragmas","-nostdinc","-nostdinc++","-g","-std=gnu++1z","-Wall","-Wextra","-Wextra","-fexceptions","-mthreads","-fsyntax-only","-m64","--target=x86_64-w64-mingw32","-DUNICODE","-D_UNICODE","-DWIN32","-DMINGW_HAS_SECURE_API","-DQT_QML_DEBUG","-DQT_WIDGETS_LIB","-DQT_GUI_LIB","-DQT_NETWORK_LIB","-DQT_CORE_LIB","-DQT_NEEDS_QMAIN","-DQ_CREATOR_RUN","-DQT_ANNOTATE_FUNCTION(x)=__attribute__((annotate(#x)))","-ID:\\Qt6\\Tools\\QtCreator\\share\\qtcreator\\cplusplus\\wrappedMingwHeaders","-ID:\\Qt6\\Tools\\QtCreator\\share\\qtcreator\\cplusplus\\wrappedQtHeaders","-ID:\\Qt6\\Tools\\QtCreator\\share\\qtcreator\\cplusplus\\wrappedQtHeaders\\QtCore","-IE:\\project\\llfc_chat","-ID:\\Qt6\\6.10.0\\mingw_64\\include","-ID:\\Qt6\\6.10.0\\mingw_64\\include\\QtWidgets","-ID:\\Qt6\\6.10.0\\mingw_64\\include\\QtGui","-ID:\\Qt6\\6.10.0\\mingw_64\\include\\QtNetwork","-ID:\\Qt6\\6.10.0\\mingw_64\\include\\QtCore","-IE:\\project\\llfc_chat\\build\\Desktop_Qt_6_10_0_MinGW_64_bit-Debug\\debug","-IE:\\project\\llfc_chat\\build\\Desktop_Qt_6_10_0_MinGW_64_bit-Debug","-ID:\\Qt6\\6.10.0\\mingw_64\\mkspecs\\win32-g++","-isystem","D:\\Qt6\\Tools\\mingw1310_64\\lib\\gcc\\x86_64-w64-mingw32\\13.1.0\\include\\c++","-isystem","D:\\Qt6\\Tools\\mingw1310_64\\lib\\gcc\\x86_64-w64-mingw32\\13.1.0\\include\\c++\\x86_64-w64-mingw32","-isystem","D:\\Qt6\\Tools\\mingw1310_64\\lib\\gcc\\x86_64-w64-mingw32\\13.1.0\\include\\c++\\backward","-isystem","D:\\Qt6\\Tools\\QtCreator\\bin\\clang\\lib\\clang\\20\\include","-isystem","D:\\Qt6\\Tools\\mingw1310_64\\x86_64-w64-mingw32\\include","-fmessage-length=0","-fdiagnostics-show-note-include-stack","-fretain-comments-from-system-headers","-fmacro-backtrace-limit=0","-ferror-limit=1000","-x","c++-header","E:\\project\\llfc_chat\\build\\Desktop_Qt_6_10_0_MinGW_64_bit-Debug\\ui_register.h"],"directory":"E:/project/llfc_chat/build/Desktop_Qt_6_10_0_MinGW_64_bit-Debug/.qtc_clangd","file":"E:/project/llfc_chat/build/Desktop_Qt_6_10_0_MinGW_64_bit-Debug/ui_register.h"},{"arguments":["clang","-Wno-documentation-unknown-command","-Wno-unknown-warning-option","-Wno-unknown-pragmas","-nostdinc","-nostdinc++","-g","-std=gnu++1z","-Wall","-Wextra","-Wextra","-fexceptions","-mthreads","-fsyntax-only","-m64","--target=x86_64-w64-mingw32","-DUNICODE","-D_UNICODE","-DWIN32","-DMINGW_HAS_SECURE_API","-DQT_QML_DEBUG","-DQT_WIDGETS_LIB","-DQT_GUI_LIB","-DQT_NETWORK_LIB","-DQT_CORE_LIB","-DQT_NEEDS_QMAIN","-DQ_CREATOR_RUN","-DQT_ANNOTATE_FUNCTION(x)=__attribute__((annotate(#x)))","-ID:\\Qt6\\Tools\\QtCreator\\share\\qtcreator\\cplusplus\\wrappedMingwHeaders","-ID:\\Qt6\\Tools\\QtCreator\\share\\qtcreator\\cplusplus\\wrappedQtHeaders","-ID:\\Qt6\\Tools\\QtCreator\\share\\qtcreator\\cplusplus\\wrappedQtHeaders\\QtCore","-IE:\\project\\llfc_chat","-ID:\\Qt6\\6.10.0\\mingw_64\\include","-ID:\\Qt6\\6.10.0\\mingw_64\\include\\QtWidgets","-ID:\\Qt6\\6.10.0\\mingw_64\\include\\QtGui","-ID:\\Qt6\\6.10.0\\mingw_64\\include\\QtNetwork","-ID:\\Qt6\\6.10.0\\mingw_64\\include\\QtCore","-IE:\\project\\llfc_chat\\build\\Desktop_Qt_6_10_0_MinGW_64_bit-Debug\\debug","-IE:\\project\\llfc_chat\\build\\Desktop_Qt_6_10_0_MinGW_64_bit-Debug","-ID:\\Qt6\\6.10.0\\mingw_64\\mkspecs\\win32-g++","-isystem","D:\\Qt6\\Tools\\mingw1310_64\\lib\\gcc\\x86_64-w64-mingw32\\13.1.0\\include\\c++","-isystem","D:\\Qt6\\Tools\\mingw1310_64\\lib\\gcc\\x86_64-w64-mingw32\\13.1.0\\include\\c++\\x86_64-w64-mingw32","-isystem","D:\\Qt6\\Tools\\mingw1310_64\\lib\\gcc\\x86_64-w64-mingw32\\13.1.0\\include\\c++\\backward","-isystem","D:\\Qt6\\Tools\\QtCreator\\bin\\clang\\lib\\clang\\20\\include","-isystem","D:\\Qt6\\Tools\\mingw1310_64\\x86_64-w64-mingw32\\include","-fmessage-length=0","-fdiagnostics-show-note-include-stack","-fretain-comments-from-system-headers","-fmacro-backtrace-limit=0","-ferror-limit=1000","-x","c++-header","E:\\project\\llfc_chat\\build\\Desktop_Qt_6_10_0_MinGW_64_bit-Debug\\ui_mainwindow.h"],"directory":"E:/project/llfc_chat/build/Desktop_Qt_6_10_0_MinGW_64_bit-Debug/.qtc_clangd","file":"E:/project/llfc_chat/build/Desktop_Qt_6_10_0_MinGW_64_bit-Debug/ui_mainwindow.h"},{"arguments":["clang","-Wno-documentation-unknown-command","-Wno-unknown-warning-option","-Wno-unknown-pragmas","-nostdinc","-nostdinc++","-g","-std=gnu++1z","-Wall","-Wextra","-Wextra","-fexceptions","-mthreads","-fsyntax-only","-m64","--target=x86_64-w64-mingw32","-DUNICODE","-D_UNICODE","-DWIN32","-DMINGW_HAS_SECURE_API","-DQT_QML_DEBUG","-DQT_WIDGETS_LIB","-DQT_GUI_LIB","-DQT_NETWORK_LIB","-DQT_CORE_LIB","-DQT_NEEDS_QMAIN","-DQ_CREATOR_RUN","-DQT_ANNOTATE_FUNCTION(x)=__attribute__((annotate(#x)))","-ID:\\Qt6\\Tools\\QtCreator\\share\\qtcreator\\cplusplus\\wrappedMingwHeaders","-ID:\\Qt6\\Tools\\QtCreator\\share\\qtcreator\\cplusplus\\wrappedQtHeaders","-ID:\\Qt6\\Tools\\QtCreator\\share\\qtcreator\\cplusplus\\wrappedQtHeaders\\QtCore","-IE:\\project\\llfc_chat","-ID:\\Qt6\\6.10.0\\mingw_64\\include","-ID:\\Qt6\\6.10.0\\mingw_64\\include\\QtWidgets","-ID:\\Qt6\\6.10.0\\mingw_64\\include\\QtGui","-ID:\\Qt6\\6.10.0\\mingw_64\\include\\QtNetwork","-ID:\\Qt6\\6.10.0\\mingw_64\\include\\QtCore","-IE:\\project\\llfc_chat\\build\\Desktop_Qt_6_10_0_MinGW_64_bit-Debug\\debug","-IE:\\project\\llfc_chat\\build\\Desktop_Qt_6_10_0_MinGW_64_bit-Debug","-ID:\\Qt6\\6.10.0\\mingw_64\\mkspecs\\win32-g++","-isystem","D:\\Qt6\\Tools\\mingw1310_64\\lib\\gcc\\x86_64-w64-mingw32\\13.1.0\\include\\c++","-isystem","D:\\Qt6\\Tools\\mingw1310_64\\lib\\gcc\\x86_64-w64-mingw32\\13.1.0\\include\\c++\\x86_64-w64-mingw32","-isystem","D:\\Qt6\\Tools\\mingw1310_64\\lib\\gcc\\x86_64-w64-mingw32\\13.1.0\\include\\c++\\backward","-isystem","D:\\Qt6\\Tools\\QtCreator\\bin\\clang\\lib\\clang\\20\\include","-isystem","D:\\Qt6\\Tools\\mingw1310_64\\x86_64-w64-mingw32\\include","-fmessage-length=0","-fdiagnostics-show-note-include-stack","-fretain-comments-from-system-headers","-fmacro-backtrace-limit=0","-ferror-limit=1000","-x","c++-header","E:\\project\\llfc_chat\\build\\Desktop_Qt_6_10_0_MinGW_64_bit-Debug\\ui_registeryes.h"],"directory":"E:/project/llfc_chat/build/Desktop_Qt_6_10_0_MinGW_64_bit-Debug/.qtc_clangd","file":"E:/project/llfc_chat/build/Desktop_Qt_6_10_0_MinGW_64_bit-Debug/ui_registeryes.h"},{"arguments":["clang","-Wno-documentation-unknown-command","-Wno-unknown-warning-option","-Wno-unknown-pragmas","-nostdinc","-nostdinc++","-g","-std=gnu++1z","-Wall","-Wextra","-Wextra","-fexceptions","-mthreads","-fsyntax-only","-m64","--target=x86_64-w64-mingw32","-DUNICODE","-D_UNICODE","-DWIN32","-DMINGW_HAS_SECURE_API","-DQT_QML_DEBUG","-DQT_WIDGETS_LIB","-DQT_GUI_LIB","-DQT_NETWORK_LIB","-DQT_CORE_LIB","-DQT_NEEDS_QMAIN","-DQ_CREATOR_RUN","-DQT_ANNOTATE_FUNCTION(x)=__attribute__((annotate(#x)))","-ID:\\Qt6\\Tools\\QtCreator\\share\\qtcreator\\cplusplus\\wrappedMingwHeaders","-ID:\\Qt6\\Tools\\QtCreator\\share\\qtcreator\\cplusplus\\wrappedQtHeaders","-ID:\\Qt6\\Tools\\QtCreator\\share\\qtcreator\\cplusplus\\wrappedQtHeaders\\QtCore","-IE:\\project\\llfc_chat","-ID:\\Qt6\\6.10.0\\mingw_64\\include","-ID:\\Qt6\\6.10.0\\mingw_64\\include\\QtWidgets","-ID:\\Qt6\\6.10.0\\mingw_64\\include\\QtGui","-ID:\\Qt6\\6.10.0\\mingw_64\\include\\QtNetwork","-ID:\\Qt6\\6.10.0\\mingw_64\\include\\QtCore","-IE:\\project\\llfc_chat\\build\\Desktop_Qt_6_10_0_MinGW_64_bit-Debug\\debug","-IE:\\project\\llfc_chat\\build\\Desktop_Qt_6_10_0_MinGW_64_bit-Debug","-ID:\\Qt6\\6.10.0\\mingw_64\\mkspecs\\win32-g++","-isystem","D:\\Qt6\\Tools\\mingw1310_64\\lib\\gcc\\x86_64-w64-mingw32\\13.1.0\\include\\c++","-isystem","D:\\Qt6\\Tools\\mingw1310_64\\lib\\gcc\\x86_64-w64-mingw32\\13.1.0\\include\\c++\\x86_64-w64-mingw32","-isystem","D:\\Qt6\\Tools\\mingw1310_64\\lib\\gcc\\x86_64-w64-mingw32\\13.1.0\\include\\c++\\backward","-isystem","D:\\Qt6\\Tools\\QtCreator\\bin\\clang\\lib\\clang\\20\\include","-isystem","D:\\Qt6\\Tools\\mingw1310_64\\x86_64-w64-mingw32\\include","-fmessage-length=0","-fdiagnostics-show-note-include-stack","-fretain-comments-from-system-headers","-fmacro-backtrace-limit=0","-ferror-limit=1000","-x","c++-header","E:\\project\\llfc_chat\\build\\Desktop_Qt_6_10_0_MinGW_64_bit-Debug\\ui_Reset.h"],"directory":"E:/project/llfc_chat/build/Desktop_Qt_6_10_0_MinGW_64_bit-Debug/.qtc_clangd","file":"E:/project/llfc_chat/build/Desktop_Qt_6_10_0_MinGW_64_bit-Debug/ui_Reset.h"}]